miniobj/__init__.py
miniobj/exporter.py
miniobj/loader.py
miniobj/miniobj.py
miniobj-0.0.2.dist-info/LICENSE
miniobj-0.0.2.dist-info/METADATA
miniobj-0.0.2.dist-info/WHEEL
miniobj-0.0.2.dist-info/top_level.txt
miniobj-0.0.2.dist-info/RECORD
