Metadata-Version: 2.1
Name: miniobj
Version: 0.0.2
Summary: A minimalistic Python library for loading Wavefront OBJ files.
License: MIT License
Classifier: Development Status :: 3 - Alpha
Classifier: Programming Language :: Python
Requires-Python: >=3.7.0
License-File: LICENSE
Requires-Dist: tqdm
Requires-Dist: numpy
Requires-Dist: pillow
